yumemi/__init__.py
yumemi/_rhash/__init__.py
yumemi/_rhash/libname.py
yumemi/_rhash/rhash.py
yumemi/anidb.py
yumemi/cli.py
yumemi/exceptions.py
yumemi/py.typed
yumemi-2.1.0.dist-info/LICENSE
yumemi-2.1.0.dist-info/METADATA
yumemi-2.1.0.dist-info/WHEEL
yumemi-2.1.0.dist-info/entry_points.txt
yumemi-2.1.0.dist-info/RECORD
